Metadata-Version: 2.1
Name: sparklightautoml-dev
Version: 0.3.2
Summary: Spark-based distribution version of fast and customizable framework for automatic ML model creation (AutoML)
Home-page: https://lightautoml.readthedocs.io/en/latest/
License: Apache-2.0
Author: Alexander Ryzhkov
Author-email: alexmryzhkov@gmail.com
Requires-Python: >=3.8,<3.10
Classifier: Development Status :: 3 - Alpha
Classifier: Environment :: Console
Classifier: Intended Audience :: Science/Research
Classifier: License :: OSI Approved :: Apache Software License
Classifier: Natural Language :: Russian
Classifier: Operating System :: OS Independent
Classifier: Programming Language :: Python :: 3
Classifier: Programming Language :: Python :: 3.8
Classifier: Programming Language :: Python :: 3.9
Classifier: Topic :: Scientific/Engineering :: Artificial Intelligence
Classifier: Typing :: Typed
Requires-Dist: hdfs (>=2.7.0,<3.0.0)
Requires-Dist: lightautoml (==0.3.7.1)
Requires-Dist: onnxmltools (>=1.11.0,<2.0.0)
Requires-Dist: poetry-core (>=1.0.0,<2.0.0)
Requires-Dist: pyarrow (>=1.0.0)
Requires-Dist: pyspark (==3.2.0)
Requires-Dist: synapseml (==0.9.5)
Requires-Dist: toposort (==1.7)
Requires-Dist: weasyprint (==52.5)
Project-URL: Repository, https://github.com/fonhorst/LightAutoML_Spark
